thumbor_expire/__init__.py
thumbor_expire/base64_hmac_sha1_expire.py
thumbor_expire/crypto.py
thumbor_expire-0.1.3.dist-info/LICENSE
thumbor_expire-0.1.3.dist-info/WHEEL
thumbor_expire-0.1.3.dist-info/METADATA
thumbor_expire-0.1.3.dist-info/RECORD
